haptk/__init__.py
haptk/circle_tree.py
haptk/index_tree.py
haptk/iterate_tree.py
haptk/leaf_neighbors.py
haptk/lib.py
haptk/match_tree.py
haptk/normal_tree.py
haptk/utils.py
haptk-0.0.9.dist-info/METADATA
haptk-0.0.9.dist-info/WHEEL
haptk-0.0.9.dist-info/top_level.txt
haptk-0.0.9.dist-info/RECORD
