Metadata-Version: 2.1
Name: haptk
Version: 0.0.9
Summary: HAPTK
Author-email: "Osma S. Rautila" <author@example.com>
Project-URL: Homepage, https://github.com/xosxos/haptk
Project-URL: Issues, https://github.com/xosxos/haptk/issues
Classifier: Programming Language :: Python :: 3
Classifier: License :: OSI Approved :: MIT License
Classifier: Operating System :: OS Independent
Requires-Python: >=3.10
Requires-Dist: ete3 ==3.1.3
Requires-Dist: rustworkx ==0.14.2
Requires-Dist: pyqt5 ==5.15.10
Requires-Dist: scipy ==1.14.1
Requires-Dist: matplotlib >=3.8.4
Requires-Dist: numpy >=1.24.4
